README.md
setup.py
neuralnexus/__init__.py
neuralnexus.egg-info/PKG-INFO
neuralnexus.egg-info/SOURCES.txt
neuralnexus.egg-info/dependency_links.txt
neuralnexus.egg-info/requires.txt
neuralnexus.egg-info/top_level.txt
neuralnexus/ranking/__init__.py
neuralnexus/ranking/losses.py
neuralnexus/ranking/oop.py
neuralnexus/ranking/utils.py