Metadata-Version: 2.1
Name: neuralnexus
Version: 0.0.2
Summary: neuralnexus - An open source, low-code machine learning framework in Python.
Home-page: https://github.com/azharlabs/neuralnexus
Author: Mohamed Azharudeen
Author-email: azhar@neuralnexus.cloud
License: MIT
Platform: UNKNOWN
Classifier: License :: OSI Approved :: MIT License
Classifier: Programming Language :: Python :: 3.8
Classifier: Programming Language :: Python :: 3.9
Classifier: Programming Language :: Python :: 3.10
Classifier: Topic :: Scientific/Engineering :: Artificial Intelligence
Classifier: License :: OSI Approved :: MIT License
Classifier: Operating System :: OS Independent
Requires-Python: >=3.8
Provides-Extra: test
Provides-Extra: full
